getmodules/__init__.py
getmodules/getModulesName.py
modules_name_from_code-1.0.1.dist-info/METADATA
modules_name_from_code-1.0.1.dist-info/WHEEL
modules_name_from_code-1.0.1.dist-info/top_level.txt
modules_name_from_code-1.0.1.dist-info/RECORD
