Metadata-Version: 2.1
Name: modules-name-from-code
Version: 1.0.1
Summary: Get modules name from your python code
Home-page: https://github.com/ajb3296/modules-name-from-code
Author: An Jaebeom
Author-email: ajb8533296@gmail.com
License: MIT
Platform: UNKNOWN
Classifier: Programming Language :: Python :: 3
Classifier: License :: OSI Approved :: MIT License
Classifier: Operating System :: OS Independent
